django_database_translation/__init__.py
django_database_translation/admin.py
django_database_translation/apps.py
django_database_translation/fields.py
django_database_translation/forms.py
django_database_translation/managers.py
django_database_translation/models.py
django_database_translation/signals.py
django_database_translation/utils.py
django_database_translation/migrations/__init__.py
django_database_translation-1.1.5.dist-info/LICENCE.txt
django_database_translation-1.1.5.dist-info/METADATA
django_database_translation-1.1.5.dist-info/WHEEL
django_database_translation-1.1.5.dist-info/top_level.txt
django_database_translation-1.1.5.dist-info/RECORD
