Metadata-Version: 2.1
Name: django-database-translation
Version: 1.1.5
Summary: Package to handle database translation in your Django apps
Home-page: https://github.com/Jordan-Kowal/django_database_translation
Author: Jordan Kowal
Author-email: kowaljordan@gmail.com
License: MIT
Download-URL: https://github.com/Jordan-Kowal/django_database_translation/archive/v1.1.5.tar.gz
Keywords: django,database,db,translation,translate,backend
Platform: UNKNOWN
Classifier: Development Status :: 5 - Production/Stable
Classifier: Intended Audience :: Developers
Classifier: Topic :: Software Development :: Build Tools
Classifier: License :: OSI Approved :: MIT License
Classifier: Programming Language :: Python :: 3
